SpaceXRM/MyFileHandling.py
SpaceXRM/MyLogo.py
SpaceXRM/MyRequests.py
SpaceXRM/MySecure.py
SpaceXRM/MySelenium copy.py
SpaceXRM/MySelenium.py
SpaceXRM/MySettings.py
SpaceXRM/MySolver.py
SpaceXRM/MyTempMail.py
SpaceXRM/__init__.py
SpaceXRM-0.0.7.dist-info/LICENSE
SpaceXRM-0.0.7.dist-info/METADATA
SpaceXRM-0.0.7.dist-info/WHEEL
SpaceXRM-0.0.7.dist-info/top_level.txt
SpaceXRM-0.0.7.dist-info/RECORD
