Metadata-Version: 2.1
Name: SpaceXRM
Version: 0.0.7
Summary: Special package
Author: Ramiz Al-Jabri
Author-email: <ramzalgabry232@gmail.com>
Keywords: python,selenium,playwright,selenium_profiles,curl_cffi,requests
Classifier: Development Status :: 1 - Planning
Classifier: Intended Audience :: Developers
Classifier: Programming Language :: Python :: 3
Classifier: Operating System :: Microsoft :: Windows
License-File: LICENSE
Requires-Dist: pycountry
Requires-Dist: phonenumbers
Requires-Dist: phone-iso3166
Requires-Dist: colorama
Requires-Dist: curl-cffi
Requires-Dist: selenium-profiles
Requires-Dist: playwright
Requires-Dist: selenium
Requires-Dist: ua-generator
Requires-Dist: bs4
Requires-Dist: names
